piqp/__init__.py
piqp/__init__.pyi
piqp/instruction_set.cpython-39-i386-linux-gnu.so
piqp/piqp_python.cpython-39-i386-linux-gnu.so
piqp.libs/libgcc_s-e1925712.so.1
piqp.libs/libstdc++-b2d5af4b.so.6.0.33
piqp-0.6.2.dist-info/METADATA
piqp-0.6.2.dist-info/WHEEL
piqp-0.6.2.dist-info/RECORD
piqp-0.6.2.dist-info/licenses/LICENSE
