Metadata-Version: 2.1
Name: piqp
Version: 0.6.2
Summary: A Proximal Interior Point Quadratic Programming solver
Author-Email: Roland Schwan <roland.schwan@epfl.ch>
License: BSD 2-Clause License
Project-URL: Homepage, https://predict-epfl.github.io/piqp/
Requires-Python: >=3.7
Requires-Dist: numpy
Requires-Dist: scipy
